ffpass_next/__init__.py
ffpass_next-0.1.2.dist-info/LICENSE
ffpass_next-0.1.2.dist-info/METADATA
ffpass_next-0.1.2.dist-info/WHEEL
ffpass_next-0.1.2.dist-info/entry_points.txt
ffpass_next-0.1.2.dist-info/top_level.txt
ffpass_next-0.1.2.dist-info/RECORD
