Metadata-Version: 2.1
Name: ffpass-next
Version: 0.1.2
Summary: Import and Export passwords for Firefox
Home-page: https://github.com/bwInfoSec/ffpass
Author: Stefan Machmeier
Author-email: stefan-machmeier@outlook.com
License: MIT
Classifier: Topic :: Utilities
Classifier: Topic :: Security :: Cryptography
Requires-Python: >=3.6
License-File: LICENSE
Requires-Dist: pyasn1
Requires-Dist: pycryptodome
